README.md
licence.txt
setup.cfg
setup.py
OptionChainMonthlyJoshuaHrs/OptionChainMonthlyJoshuaHrs.py
OptionChainMonthlyJoshuaHrs/__init__.py
OptionChainMonthlyJoshuaHrs.egg-info/PKG-INFO
OptionChainMonthlyJoshuaHrs.egg-info/SOURCES.txt
OptionChainMonthlyJoshuaHrs.egg-info/dependency_links.txt
OptionChainMonthlyJoshuaHrs.egg-info/top_level.txt
OptionChainMonthlyJoshuaHrs.egg-info/zip-safe