Metadata-Version: 2.1
Name: OptionChainMonthlyJoshuaHrs
Version: 0.1
Summary: Private Module for Joshua 
License-File: licence.txt
